impi-2019.4.243.dist-info/METADATA
impi-2019.4.243.dist-info/RECORD
impi-2019.4.243.dist-info/WHEEL
impi-2019.4.243.dist-info/top_level.txt
intellibs/bin/IMB-MPI1
intellibs/bin/IMB-MT
intellibs/bin/IMB-NBC
intellibs/bin/IMB-P2P
intellibs/bin/IMB-RMA
intellibs/bin/cpuinfo
intellibs/bin/hydra_bstrap_proxy
intellibs/bin/hydra_nameserver
intellibs/bin/hydra_pmi_proxy
intellibs/bin/impi_info
intellibs/bin/mpiexec
intellibs/bin/mpiexec.hydra
intellibs/bin/mpirun
intellibs/bin/mpitune
intellibs/bin/mpivars.csh
intellibs/bin/mpivars.sh
intellibs/bin/legacy/hydra_nameserver
intellibs/bin/legacy/hydra_persist
intellibs/bin/legacy/mpiexec.hydra
intellibs/bin/legacy/pmi_proxy
intellibs/bin/libfabric/fi_info
intellibs/bin/libfabric/src.tgz
intellibs/bin/tune/_collections.so
intellibs/bin/tune/_functools.so
intellibs/bin/tune/_io.so
intellibs/bin/tune/_random.so
intellibs/bin/tune/_struct.so
intellibs/bin/tune/binascii.so
intellibs/bin/tune/cStringIO.so
intellibs/bin/tune/fcntl.so
intellibs/bin/tune/itertools.so
intellibs/bin/tune/math.so
intellibs/bin/tune/mpitune
intellibs/bin/tune/operator.so
intellibs/bin/tune/select.so
intellibs/bin/tune/time.so
intellibs/etc/collectives.conf
intellibs/etc/pt2pt.conf
intellibs/etc/tuning_knl_ofi.dat
intellibs/etc/tuning_knl_shm-ofi.dat
intellibs/etc/tuning_skx_ofi.dat
intellibs/etc/tuning_skx_shm-ofi.dat
intellibs/etc/vt.conf
intellibs/etc/vtfs.conf
intellibs/etc/vtim.conf
intellibs/etc/vtmc.conf
intellibs/etc/conda/activate.d/mpivars.activate.sh
intellibs/etc/conda/deactivate.d/mpivars.deactivate.sh
intellibs/etc/tune_cfg/impi2018.py
intellibs/etc/tune_cfg/impi2019.py
intellibs/etc/tune_cfg/sample_allgather.cfg
intellibs/etc/tune_cfg/sample_allgatherv.cfg
intellibs/etc/tune_cfg/sample_allreduce.cfg
intellibs/etc/tune_cfg/sample_alltoall.cfg
intellibs/etc/tune_cfg/sample_alltoallv.cfg
intellibs/etc/tune_cfg/sample_barrier.cfg
intellibs/etc/tune_cfg/sample_bcast.cfg
intellibs/etc/tune_cfg/sample_gather.cfg
intellibs/etc/tune_cfg/sample_gatherv.cfg
intellibs/etc/tune_cfg/sample_legacy_format.cfg
