Metadata-Version: 2.1
Name: impi
Version: 2019.4.243
Summary: Intel(R) MPI Runtime
Home-page: https://software.intel.com/en-us/articles/empowering-science-with-high-performance-python
Author: Intel Corporation
Author-email: scripting@intel.com
License: Proprietary - Intel
Platform: UNKNOWN
Classifier: Development Status :: 5 - Production/Stable
Classifier: Operating System :: MacOS
Classifier: Operating System :: Microsoft :: Windows
Classifier: Operating System :: POSIX
Classifier: Operating System :: Unix
Classifier: Intended Audience :: Developers
Classifier: Intended Audience :: Education
Classifier: Intended Audience :: System Administrators
Classifier: Intended Audience :: Other Audience
Classifier: Intended Audience :: Science/Research
Classifier: Topic :: Software Development :: Libraries
Classifier: License :: Other/Proprietary License
